{
  "top_users": [
    {
      "name": "Luan Araújo",
      "commits": 47
    },
    {
      "name": "braynerdev",
      "commits": 12
    },
    {
      "name": "4stuno",
      "commits": 8
    },
    {
      "name": "Adelson",
      "commits": 7
    },
    {
      "name": "4stun0",
      "commits": 3
    },
    {
      "name": "Natalia Bento",
      "commits": 2
    },
    {
      "name": "Thiago Mariano",
      "commits": 1
    },
    {
      "name": "Grande Recife - CTM",
      "commits": 1
    }
  ],
  "repositories": {
    "itinerarios": {
      "commits": [
        {
          "sha": "8d32be5",
          "author": "braynerdev",
          "date": "2025-08-29T19:58:25Z",
          "additions": 156,
          "deletions": 0,
          "total_lines": 156
        },
        {
          "sha": "ba934fa",
          "author": "Adelson",
          "date": "2025-08-27T12:56:03Z",
          "additions": 3,
          "deletions": 5,
          "total_lines": 8
        },
        {
          "sha": "c01f595",
          "author": "Adelson",
          "date": "2025-08-26T19:25:46Z",
          "additions": 1,
          "deletions": 1,
          "total_lines": 2
        },
        {
          "sha": "61c7b6b",
          "author": "Adelson",
          "date": "2025-08-26T19:18:40Z",
          "additions": 33,
          "deletions": 15,
          "total_lines": 48
        },
        {
          "sha": "f90c045",
          "author": "Natalia Bento",
          "date": "2025-08-26T18:28:15Z",
          "additions": 0,
          "deletions": 0,
          "total_lines": 0
        }
      ],
      "total_additions": 193,
      "total_deletions": 21,
      "total_lines": 214
    },
    "pesquisa-dipe": {
      "commits": [
        {
          "sha": "f1e27c2",
          "author": "braynerdev",
          "date": "2025-08-27T12:00:38Z",
          "additions": 24,
          "deletions": 4,
          "total_lines": 28
        },
        {
          "sha": "66b9b56",
          "author": "braynerdev",
          "date": "2025-08-27T11:41:23Z",
          "additions": 23661,
          "deletions": 30969,
          "total_lines": 54630
        },
        {
          "sha": "88be271",
          "author": "braynerdev",
          "date": "2025-08-26T17:50:23Z",
          "additions": 523,
          "deletions": 525,
          "total_lines": 1048
        },
        {
          "sha": "0d13e75",
          "author": "braynerdev",
          "date": "2025-08-26T03:32:50Z",
          "additions": 64732,
          "deletions": 152148,
          "total_lines": 216880
        },
        {
          "sha": "75c8e5e",
          "author": "braynerdev",
          "date": "2025-08-25T20:06:04Z",
          "additions": 210042,
          "deletions": 0,
          "total_lines": 210042
        }
      ],
      "total_additions": 298982,
      "total_deletions": 183646,
      "total_lines": 482628
    },
    "sim-ui": {
      "commits": [
        {
          "sha": "97f5b8e",
          "author": "Luan Araújo",
          "date": "2025-08-22T17:12:36Z",
          "additions": 1,
          "deletions": 1,
          "total_lines": 2
        },
        {
          "sha": "a33fe81",
          "author": "Luan Araújo",
          "date": "2025-08-22T16:58:46Z",
          "additions": 6,
          "deletions": 5,
          "total_lines": 11
        },
        {
          "sha": "bff3c28",
          "author": "Luan Araújo",
          "date": "2025-08-22T16:49:02Z",
          "additions": 59,
          "deletions": 24,
          "total_lines": 83
        },
        {
          "sha": "85c0af0",
          "author": "Luan Araújo",
          "date": "2025-08-22T15:45:47Z",
          "additions": 2,
          "deletions": 2,
          "total_lines": 4
        },
        {
          "sha": "0a1344a",
          "author": "Luan Araújo",
          "date": "2025-08-22T15:32:47Z",
          "additions": 42,
          "deletions": 1,
          "total_lines": 43
        }
      ],
      "total_additions": 110,
      "total_deletions": 33,
      "total_lines": 143
    },
    "gestao_contratos": {
      "commits": [
        {
          "sha": "d7f30f1",
          "author": "Luan Araújo",
          "date": "2025-08-21T17:25:21Z",
          "additions": 2,
          "deletions": 0,
          "total_lines": 2
        },
        {
          "sha": "23cf090",
          "author": "Luan Araújo",
          "date": "2025-08-21T17:18:26Z",
          "additions": 6,
          "deletions": 6,
          "total_lines": 12
        },
        {
          "sha": "00da69e",
          "author": "Luan Araújo",
          "date": "2025-08-21T17:13:15Z",
          "additions": 10,
          "deletions": 8,
          "total_lines": 18
        },
        {
          "sha": "31ef1de",
          "author": "Luan Araújo",
          "date": "2025-08-21T17:03:41Z",
          "additions": 1,
          "deletions": 1,
          "total_lines": 2
        },
        {
          "sha": "be02892",
          "author": "Luan Araújo",
          "date": "2025-08-21T17:04:43Z",
          "additions": 1,
          "deletions": 1,
          "total_lines": 2
        }
      ],
      "total_additions": 20,
      "total_deletions": 16,
      "total_lines": 36
    },
    "api-resources-ticketing": {
      "commits": [
        {
          "sha": "787c85a",
          "author": "Luan Araújo",
          "date": "2025-08-19T18:09:41Z",
          "additions": 1213,
          "deletions": 25,
          "total_lines": 1238
        },
        {
          "sha": "0d656b2",
          "author": "Luan Araújo",
          "date": "2025-08-19T18:09:20Z",
          "additions": 1206,
          "deletions": 21,
          "total_lines": 1227
        },
        {
          "sha": "18a3281",
          "author": "Luan Araújo",
          "date": "2025-08-19T18:09:20Z",
          "additions": 745,
          "deletions": 0,
          "total_lines": 745
        },
        {
          "sha": "760a92d",
          "author": "Luan Araújo",
          "date": "2025-08-19T18:01:57Z",
          "additions": 1,
          "deletions": 1,
          "total_lines": 2
        },
        {
          "sha": "fed45fd",
          "author": "Luan Araújo",
          "date": "2025-08-19T18:00:57Z",
          "additions": 172,
          "deletions": 8,
          "total_lines": 180
        }
      ],
      "total_additions": 3337,
      "total_deletions": 55,
      "total_lines": 3392
    },
    "glpi": {
      "commits": [
        {
          "sha": "6f46693",
          "author": "Luan Araújo",
          "date": "2025-05-07T17:33:15Z",
          "additions": 1,
          "deletions": 1,
          "total_lines": 2
        },
        {
          "sha": "45d3d44",
          "author": "Thiago Mariano",
          "date": "2025-05-07T14:46:01Z",
          "additions": 4755554,
          "deletions": 0,
          "total_lines": 4755554
        }
      ],
      "total_additions": 4755555,
      "total_deletions": 1,
      "total_lines": 4755556
    },
    "api-resources-notification": {
      "commits": [
        {
          "sha": "7ebb6d3",
          "author": "4stuno",
          "date": "2025-07-29T14:28:00Z",
          "additions": 1966,
          "deletions": 154,
          "total_lines": 2120
        },
        {
          "sha": "20f97f2",
          "author": "4stuno",
          "date": "2025-07-29T14:27:51Z",
          "additions": 1,
          "deletions": 0,
          "total_lines": 1
        },
        {
          "sha": "854d17f",
          "author": "4stuno",
          "date": "2025-07-29T14:23:38Z",
          "additions": 1,
          "deletions": 1,
          "total_lines": 2
        },
        {
          "sha": "36aff28",
          "author": "4stuno",
          "date": "2025-07-29T14:22:41Z",
          "additions": 425,
          "deletions": 1,
          "total_lines": 426
        },
        {
          "sha": "9d7cbc8",
          "author": "4stun0",
          "date": "2025-07-29T14:20:52Z",
          "additions": 1,
          "deletions": 1,
          "total_lines": 2
        }
      ],
      "total_additions": 2394,
      "total_deletions": 157,
      "total_lines": 2551
    },
    "reunioes-app-v2": {
      "commits": [
        {
          "sha": "23709c6",
          "author": "Luan Araújo",
          "date": "2025-08-14T18:14:50Z",
          "additions": 500,
          "deletions": 50,
          "total_lines": 550
        },
        {
          "sha": "6c21057",
          "author": "Luan Araújo",
          "date": "2025-08-14T18:15:28Z",
          "additions": 5,
          "deletions": 11,
          "total_lines": 16
        },
        {
          "sha": "311c4bd",
          "author": "Luan Araújo",
          "date": "2025-08-14T16:50:58Z",
          "additions": 0,
          "deletions": 7,
          "total_lines": 7
        },
        {
          "sha": "4856c44",
          "author": "Luan Araújo",
          "date": "2025-08-14T16:48:07Z",
          "additions": 150,
          "deletions": 31,
          "total_lines": 181
        },
        {
          "sha": "9b0c80c",
          "author": "Luan Araújo",
          "date": "2025-08-14T16:23:14Z",
          "additions": 139,
          "deletions": 8,
          "total_lines": 147
        }
      ],
      "total_additions": 794,
      "total_deletions": 107,
      "total_lines": 901
    },
    "sinforme": {
      "commits": [
        {
          "sha": "2562da0",
          "author": "Luan Araújo",
          "date": "2025-08-14T13:34:54Z",
          "additions": 2,
          "deletions": 2,
          "total_lines": 4
        },
        {
          "sha": "4b23f65",
          "author": "Luan Araújo",
          "date": "2025-08-14T13:30:35Z",
          "additions": 1,
          "deletions": 1,
          "total_lines": 2
        },
        {
          "sha": "bcbac84",
          "author": "Luan Araújo",
          "date": "2025-08-14T13:29:11Z",
          "additions": 3,
          "deletions": 2,
          "total_lines": 5
        },
        {
          "sha": "87b955b",
          "author": "Luan Araújo",
          "date": "2025-08-14T13:26:35Z",
          "additions": 3,
          "deletions": 3,
          "total_lines": 6
        },
        {
          "sha": "39f9d6a",
          "author": "Luan Araújo",
          "date": "2025-04-24T12:03:36Z",
          "additions": 69,
          "deletions": 84,
          "total_lines": 153
        }
      ],
      "total_additions": 78,
      "total_deletions": 92,
      "total_lines": 170
    },
    "utils": {
      "commits": [
        {
          "sha": "17531b7",
          "author": "Luan Araújo",
          "date": "2025-08-13T20:20:00Z",
          "additions": 203,
          "deletions": 0,
          "total_lines": 203
        }
      ],
      "total_additions": 203,
      "total_deletions": 0,
      "total_lines": 203
    },
    "atendimento_digital": {
      "commits": [
        {
          "sha": "9a7a43e",
          "author": "braynerdev",
          "date": "2025-08-13T18:54:21Z",
          "additions": 1521,
          "deletions": 694,
          "total_lines": 2215
        },
        {
          "sha": "2683e87",
          "author": "braynerdev",
          "date": "2025-08-04T17:55:54Z",
          "additions": 1447,
          "deletions": 585,
          "total_lines": 2032
        },
        {
          "sha": "57f9daa",
          "author": "braynerdev",
          "date": "2025-07-22T11:13:22Z",
          "additions": 1,
          "deletions": 1,
          "total_lines": 2
        },
        {
          "sha": "477b18f",
          "author": "braynerdev",
          "date": "2025-07-18T18:56:30Z",
          "additions": 1,
          "deletions": 1,
          "total_lines": 2
        },
        {
          "sha": "43b400a",
          "author": "braynerdev",
          "date": "2025-07-15T11:51:27Z",
          "additions": 170,
          "deletions": 131,
          "total_lines": 301
        }
      ],
      "total_additions": 3140,
      "total_deletions": 1412,
      "total_lines": 4552
    },
    "permissions-sim": {
      "commits": [
        {
          "sha": "7b61e95",
          "author": "Luan Araújo",
          "date": "2025-07-25T12:48:04Z",
          "additions": 53,
          "deletions": 16,
          "total_lines": 69
        },
        {
          "sha": "0407e7d",
          "author": "Luan Araújo",
          "date": "2025-05-23T14:43:48Z",
          "additions": 86,
          "deletions": 6,
          "total_lines": 92
        },
        {
          "sha": "5d54fa8",
          "author": "Luan Araújo",
          "date": "2025-05-13T19:48:24Z",
          "additions": 27,
          "deletions": 2,
          "total_lines": 29
        },
        {
          "sha": "2c78337",
          "author": "Luan Araújo",
          "date": "2025-05-06T18:44:17Z",
          "additions": 62,
          "deletions": 2,
          "total_lines": 64
        },
        {
          "sha": "0dabd89",
          "author": "4stuno",
          "date": "2025-04-24T14:31:13Z",
          "additions": 58,
          "deletions": 3,
          "total_lines": 61
        }
      ],
      "total_additions": 286,
      "total_deletions": 29,
      "total_lines": 315
    },
    "busplus-migration": {
      "commits": [
        {
          "sha": "97a0665",
          "author": "Luan Araújo",
          "date": "2025-07-22T17:17:03Z",
          "additions": 15,
          "deletions": 11,
          "total_lines": 26
        },
        {
          "sha": "b3d88af",
          "author": "Luan Araújo",
          "date": "2025-07-22T15:08:23Z",
          "additions": 45,
          "deletions": 39,
          "total_lines": 84
        },
        {
          "sha": "073417f",
          "author": "Luan Araújo",
          "date": "2025-07-17T20:11:59Z",
          "additions": 1998,
          "deletions": 0,
          "total_lines": 1998
        }
      ],
      "total_additions": 2058,
      "total_deletions": 50,
      "total_lines": 2108
    },
    "crypt-share": {
      "commits": [
        {
          "sha": "a6e44fd",
          "author": "4stuno",
          "date": "2025-07-14T19:06:13Z",
          "additions": 3,
          "deletions": 1,
          "total_lines": 4
        },
        {
          "sha": "cbbc90e",
          "author": "4stun0",
          "date": "2025-07-14T19:04:47Z",
          "additions": 3,
          "deletions": 1,
          "total_lines": 4
        },
        {
          "sha": "4103eb8",
          "author": "4stuno",
          "date": "2025-07-14T18:53:36Z",
          "additions": 4,
          "deletions": 9,
          "total_lines": 13
        },
        {
          "sha": "7848cd6",
          "author": "4stun0",
          "date": "2025-07-14T18:52:15Z",
          "additions": 4,
          "deletions": 9,
          "total_lines": 13
        },
        {
          "sha": "fb5d620",
          "author": "4stuno",
          "date": "2025-07-14T12:32:44Z",
          "additions": 35,
          "deletions": 38,
          "total_lines": 73
        }
      ],
      "total_additions": 49,
      "total_deletions": 58,
      "total_lines": 107
    },
    "scheduler-gr": {
      "commits": [
        {
          "sha": "66b6d9a",
          "author": "Luan Araújo",
          "date": "2025-07-10T20:15:53Z",
          "additions": 1812,
          "deletions": 1,
          "total_lines": 1813
        },
        {
          "sha": "c094083",
          "author": "Luan Araújo",
          "date": "2025-07-10T20:15:21Z",
          "additions": 1812,
          "deletions": 1,
          "total_lines": 1813
        },
        {
          "sha": "0bb19ff",
          "author": "Luan Araújo",
          "date": "2025-07-10T20:14:03Z",
          "additions": 1812,
          "deletions": 1,
          "total_lines": 1813
        },
        {
          "sha": "413b619",
          "author": "Grande Recife - CTM",
          "date": "2025-07-10T16:16:08Z",
          "additions": 209,
          "deletions": 0,
          "total_lines": 209
        }
      ],
      "total_additions": 5645,
      "total_deletions": 3,
      "total_lines": 5648
    },
    "datosae": {
      "commits": [
        {
          "sha": "8ab99d4",
          "author": "braynerdev",
          "date": "2025-07-08T22:28:19Z",
          "additions": 40,
          "deletions": 0,
          "total_lines": 40
        }
      ],
      "total_additions": 40,
      "total_deletions": 0,
      "total_lines": 40
    },
    "pmv-django": {
      "commits": [
        {
          "sha": "1f797e0",
          "author": "Natalia Bento",
          "date": "2025-06-27T11:39:26Z",
          "additions": 194,
          "deletions": 23,
          "total_lines": 217
        },
        {
          "sha": "7628803",
          "author": "Adelson",
          "date": "2025-06-25T19:19:57Z",
          "additions": 157,
          "deletions": 129,
          "total_lines": 286
        },
        {
          "sha": "73a01e8",
          "author": "Adelson",
          "date": "2025-06-19T16:31:55Z",
          "additions": 28,
          "deletions": 27,
          "total_lines": 55
        },
        {
          "sha": "4d4f7f8",
          "author": "Adelson",
          "date": "2025-06-18T14:18:33Z",
          "additions": 17,
          "deletions": 11,
          "total_lines": 28
        },
        {
          "sha": "922393a",
          "author": "Adelson",
          "date": "2025-06-18T12:39:29Z",
          "additions": 6,
          "deletions": 6,
          "total_lines": 12
        }
      ],
      "total_additions": 402,
      "total_deletions": 196,
      "total_lines": 598
    },
    "api-resources-planning": {
      "commits": [
        {
          "sha": "e583fe5",
          "author": "Luan Araújo",
          "date": "2025-06-25T17:18:07Z",
          "additions": 267,
          "deletions": 1184,
          "total_lines": 1451
        },
        {
          "sha": "c269ef3",
          "author": "Luan Araújo",
          "date": "2025-06-25T17:17:40Z",
          "additions": 34,
          "deletions": 8,
          "total_lines": 42
        },
        {
          "sha": "1c437e7",
          "author": "Luan Araújo",
          "date": "2025-06-25T17:16:37Z",
          "additions": 34,
          "deletions": 8,
          "total_lines": 42
        },
        {
          "sha": "3478d92",
          "author": "Luan Araújo",
          "date": "2025-06-20T18:46:56Z",
          "additions": 141,
          "deletions": 1152,
          "total_lines": 1293
        },
        {
          "sha": "d4dd8f6",
          "author": "Luan Araújo",
          "date": "2025-06-20T18:43:47Z",
          "additions": 141,
          "deletions": 1152,
          "total_lines": 1293
        }
      ],
      "total_additions": 617,
      "total_deletions": 3504,
      "total_lines": 4121
    },
    "api-resources-entities": {
      "commits": [
        {
          "sha": "c1aac74",
          "author": "Luan Araújo",
          "date": "2025-06-25T17:00:05Z",
          "additions": 34,
          "deletions": 7,
          "total_lines": 41
        },
        {
          "sha": "3708b6d",
          "author": "Luan Araújo",
          "date": "2025-06-25T16:59:36Z",
          "additions": 34,
          "deletions": 7,
          "total_lines": 41
        },
        {
          "sha": "743777a",
          "author": "Luan Araújo",
          "date": "2025-06-25T16:58:33Z",
          "additions": 34,
          "deletions": 7,
          "total_lines": 41
        },
        {
          "sha": "9ebd158",
          "author": "Luan Araújo",
          "date": "2025-06-06T13:08:07Z",
          "additions": 374,
          "deletions": 50,
          "total_lines": 424
        },
        {
          "sha": "f9d4fc4",
          "author": "Luan Araújo",
          "date": "2025-06-06T13:07:21Z",
          "additions": 372,
          "deletions": 49,
          "total_lines": 421
        }
      ],
      "total_additions": 848,
      "total_deletions": 120,
      "total_lines": 968
    }
  },
  "last_updated": "2025-08-31T22:38:50.465248-03:00"
}