{
  "top_users": [
    {
      "name": "Luan Araújo",
      "commits": 51
    },
    {
      "name": "Adelson",
      "commits": 8
    },
    {
      "name": "Danilo Torres",
      "commits": 4
    },
    {
      "name": "4stuno",
      "commits": 3
    },
    {
      "name": "Julio Cesar Roque da Silva",
      "commits": 2
    },
    {
      "name": "Natalia Bento",
      "commits": 1
    },
    {
      "name": "Grande Recife - CTM",
      "commits": 1
    },
    {
      "name": "braynerdev",
      "commits": 1
    },
    {
      "name": "Thiago Mariano",
      "commits": 1
    }
  ],
  "repositories": {
    "pmv-django": {
      "commits": [
        {
          "sha": "1f797e0",
          "author": "Natalia Bento",
          "date": "2025-06-27T11:39:26Z",
          "additions": 194,
          "deletions": 23,
          "total_lines": 217
        },
        {
          "sha": "7628803",
          "author": "Adelson",
          "date": "2025-06-25T19:19:57Z",
          "additions": 157,
          "deletions": 129,
          "total_lines": 286
        },
        {
          "sha": "73a01e8",
          "author": "Adelson",
          "date": "2025-06-19T16:31:55Z",
          "additions": 28,
          "deletions": 27,
          "total_lines": 55
        },
        {
          "sha": "4d4f7f8",
          "author": "Adelson",
          "date": "2025-06-18T14:18:33Z",
          "additions": 17,
          "deletions": 11,
          "total_lines": 28
        },
        {
          "sha": "922393a",
          "author": "Adelson",
          "date": "2025-06-18T12:39:29Z",
          "additions": 6,
          "deletions": 6,
          "total_lines": 12
        }
      ],
      "total_additions": 402,
      "total_deletions": 196,
      "total_lines": 598
    },
    "sim-ui": {
      "commits": [
        {
          "sha": "15edc59",
          "author": "Grande Recife - CTM",
          "date": "2025-06-19T19:59:00Z",
          "additions": 1118,
          "deletions": 1050,
          "total_lines": 2168
        },
        {
          "sha": "37f46b5",
          "author": "4stuno",
          "date": "2025-06-19T19:56:54Z",
          "additions": 432,
          "deletions": 459,
          "total_lines": 891
        },
        {
          "sha": "0bca921",
          "author": "Julio Cesar Roque da Silva",
          "date": "2025-06-19T19:54:53Z",
          "additions": 1,
          "deletions": 1,
          "total_lines": 2
        },
        {
          "sha": "a454273",
          "author": "Julio Cesar Roque da Silva",
          "date": "2025-06-19T19:54:21Z",
          "additions": 431,
          "deletions": 458,
          "total_lines": 889
        },
        {
          "sha": "612db58",
          "author": "4stuno",
          "date": "2025-06-19T18:42:40Z",
          "additions": 94,
          "deletions": 47,
          "total_lines": 141
        }
      ],
      "total_additions": 2076,
      "total_deletions": 2015,
      "total_lines": 4091
    },
    "api-resources-planning": {
      "commits": [
        {
          "sha": "e583fe5",
          "author": "Luan Araújo",
          "date": "2025-06-25T17:18:07Z",
          "additions": 267,
          "deletions": 1184,
          "total_lines": 1451
        },
        {
          "sha": "c269ef3",
          "author": "Luan Araújo",
          "date": "2025-06-25T17:17:40Z",
          "additions": 34,
          "deletions": 8,
          "total_lines": 42
        },
        {
          "sha": "1c437e7",
          "author": "Luan Araújo",
          "date": "2025-06-25T17:16:37Z",
          "additions": 34,
          "deletions": 8,
          "total_lines": 42
        },
        {
          "sha": "3478d92",
          "author": "Luan Araújo",
          "date": "2025-06-20T18:46:56Z",
          "additions": 141,
          "deletions": 1152,
          "total_lines": 1293
        },
        {
          "sha": "d4dd8f6",
          "author": "Luan Araújo",
          "date": "2025-06-20T18:43:47Z",
          "additions": 141,
          "deletions": 1152,
          "total_lines": 1293
        }
      ],
      "total_additions": 617,
      "total_deletions": 3504,
      "total_lines": 4121
    },
    "api-resources-entities": {
      "commits": [
        {
          "sha": "c1aac74",
          "author": "Luan Araújo",
          "date": "2025-06-25T17:00:05Z",
          "additions": 34,
          "deletions": 7,
          "total_lines": 41
        },
        {
          "sha": "3708b6d",
          "author": "Luan Araújo",
          "date": "2025-06-25T16:59:36Z",
          "additions": 34,
          "deletions": 7,
          "total_lines": 41
        },
        {
          "sha": "743777a",
          "author": "Luan Araújo",
          "date": "2025-06-25T16:58:33Z",
          "additions": 34,
          "deletions": 7,
          "total_lines": 41
        },
        {
          "sha": "9ebd158",
          "author": "Luan Araújo",
          "date": "2025-06-06T13:08:07Z",
          "additions": 374,
          "deletions": 50,
          "total_lines": 424
        },
        {
          "sha": "f9d4fc4",
          "author": "Luan Araújo",
          "date": "2025-06-06T13:07:21Z",
          "additions": 372,
          "deletions": 49,
          "total_lines": 421
        }
      ],
      "total_additions": 848,
      "total_deletions": 120,
      "total_lines": 968
    },
    "api-resources-sso": {
      "commits": [
        {
          "sha": "e630789",
          "author": "Luan Araújo",
          "date": "2025-06-25T14:06:24Z",
          "additions": 2,
          "deletions": 2,
          "total_lines": 4
        },
        {
          "sha": "5d8004f",
          "author": "Luan Araújo",
          "date": "2025-06-25T14:05:51Z",
          "additions": 2,
          "deletions": 2,
          "total_lines": 4
        },
        {
          "sha": "c72b0ae",
          "author": "Luan Araújo",
          "date": "2025-06-25T14:03:36Z",
          "additions": 2,
          "deletions": 2,
          "total_lines": 4
        },
        {
          "sha": "14dc35a",
          "author": "Luan Araújo",
          "date": "2025-06-25T13:52:27Z",
          "additions": 32,
          "deletions": 5,
          "total_lines": 37
        },
        {
          "sha": "d80e66d",
          "author": "Luan Araújo",
          "date": "2025-06-25T13:50:52Z",
          "additions": 32,
          "deletions": 5,
          "total_lines": 37
        }
      ],
      "total_additions": 70,
      "total_deletions": 16,
      "total_lines": 86
    },
    "itinerarios": {
      "commits": [
        {
          "sha": "b3bf642",
          "author": "braynerdev",
          "date": "2025-06-20T13:29:52Z",
          "additions": 1179,
          "deletions": 549,
          "total_lines": 1728
        },
        {
          "sha": "045c7f7",
          "author": "Luan Araújo",
          "date": "2025-05-14T15:46:38Z",
          "additions": 1,
          "deletions": 1,
          "total_lines": 2
        },
        {
          "sha": "b82f929",
          "author": "Luan Araújo",
          "date": "2025-04-08T12:12:11Z",
          "additions": 1,
          "deletions": 1,
          "total_lines": 2
        },
        {
          "sha": "93fb8e1",
          "author": "Luan Araújo",
          "date": "2025-04-08T11:43:17Z",
          "additions": 523,
          "deletions": 20178,
          "total_lines": 20701
        },
        {
          "sha": "25775a1",
          "author": "Luan Araújo",
          "date": "2025-04-08T11:41:24Z",
          "additions": 437,
          "deletions": 428,
          "total_lines": 865
        }
      ],
      "total_additions": 2141,
      "total_deletions": 21157,
      "total_lines": 23298
    },
    "avaliacao-desempenho": {
      "commits": [
        {
          "sha": "68065c3",
          "author": "Luan Araújo",
          "date": "2025-06-18T11:58:44Z",
          "additions": 0,
          "deletions": 2048,
          "total_lines": 2048
        },
        {
          "sha": "14544d4",
          "author": "Luan Araújo",
          "date": "2025-06-18T11:58:19Z",
          "additions": 0,
          "deletions": 2048,
          "total_lines": 2048
        },
        {
          "sha": "acec6d6",
          "author": "Luan Araújo",
          "date": "2025-06-18T11:57:42Z",
          "additions": 0,
          "deletions": 2048,
          "total_lines": 2048
        },
        {
          "sha": "5433cea",
          "author": "Luan Araújo",
          "date": "2025-06-18T11:33:42Z",
          "additions": 608,
          "deletions": 406,
          "total_lines": 1014
        },
        {
          "sha": "9c17d26",
          "author": "Luan Araújo",
          "date": "2025-06-18T11:33:15Z",
          "additions": 555,
          "deletions": 57,
          "total_lines": 612
        }
      ],
      "total_additions": 1163,
      "total_deletions": 6607,
      "total_lines": 7770
    },
    "sim-docs": {
      "commits": [
        {
          "sha": "ffd297c",
          "author": "Luan Araújo",
          "date": "2025-06-12T13:10:41Z",
          "additions": 4,
          "deletions": 4,
          "total_lines": 8
        },
        {
          "sha": "f6e1d11",
          "author": "Luan Araújo",
          "date": "2025-06-12T13:09:51Z",
          "additions": 16,
          "deletions": 16,
          "total_lines": 32
        },
        {
          "sha": "e8e7287",
          "author": "Luan Araújo",
          "date": "2025-06-12T13:04:49Z",
          "additions": 1422,
          "deletions": 2,
          "total_lines": 1424
        },
        {
          "sha": "699682f",
          "author": "Luan Araújo",
          "date": "2025-06-12T11:24:26Z",
          "additions": 2,
          "deletions": 0,
          "total_lines": 2
        }
      ],
      "total_additions": 1444,
      "total_deletions": 22,
      "total_lines": 1466
    },
    "reunioes-app": {
      "commits": [
        {
          "sha": "3ee92c5",
          "author": "Luan Araújo",
          "date": "2025-06-10T13:32:33Z",
          "additions": 6,
          "deletions": 2,
          "total_lines": 8
        },
        {
          "sha": "cbec9ba",
          "author": "Luan Araújo",
          "date": "2025-06-10T13:32:06Z",
          "additions": 6,
          "deletions": 2,
          "total_lines": 8
        },
        {
          "sha": "e3b6d10",
          "author": "Luan Araújo",
          "date": "2025-04-24T14:55:57Z",
          "additions": 55,
          "deletions": 34,
          "total_lines": 89
        },
        {
          "sha": "a2ba62a",
          "author": "Luan Araújo",
          "date": "2025-04-24T14:55:12Z",
          "additions": 55,
          "deletions": 34,
          "total_lines": 89
        },
        {
          "sha": "2ffa78c",
          "author": "Luan Araújo",
          "date": "2025-04-24T14:52:52Z",
          "additions": 1,
          "deletions": 1,
          "total_lines": 2
        }
      ],
      "total_additions": 123,
      "total_deletions": 73,
      "total_lines": 196
    },
    "pmv-horarios-gr": {
      "commits": [
        {
          "sha": "7dd1a58",
          "author": "Luan Araújo",
          "date": "2025-06-03T12:39:22Z",
          "additions": 64,
          "deletions": 41,
          "total_lines": 105
        },
        {
          "sha": "368fcf5",
          "author": "Luan Araújo",
          "date": "2025-06-03T11:34:34Z",
          "additions": 10,
          "deletions": 11,
          "total_lines": 21
        },
        {
          "sha": "434cdad",
          "author": "Luan Araújo",
          "date": "2025-06-02T20:08:10Z",
          "additions": 3,
          "deletions": 8,
          "total_lines": 11
        },
        {
          "sha": "1d06da9",
          "author": "Luan Araújo",
          "date": "2025-06-02T19:59:36Z",
          "additions": 2,
          "deletions": 3,
          "total_lines": 5
        },
        {
          "sha": "f47fd40",
          "author": "Luan Araújo",
          "date": "2025-06-02T19:57:48Z",
          "additions": 1,
          "deletions": 0,
          "total_lines": 1
        }
      ],
      "total_additions": 80,
      "total_deletions": 63,
      "total_lines": 143
    },
    "permissions-sim": {
      "commits": [
        {
          "sha": "5d54fa8",
          "author": "Luan Araújo",
          "date": "2025-05-13T19:48:24Z",
          "additions": 27,
          "deletions": 2,
          "total_lines": 29
        },
        {
          "sha": "2c78337",
          "author": "Luan Araújo",
          "date": "2025-05-06T18:44:17Z",
          "additions": 62,
          "deletions": 2,
          "total_lines": 64
        },
        {
          "sha": "0dabd89",
          "author": "4stuno",
          "date": "2025-04-24T14:31:13Z",
          "additions": 58,
          "deletions": 3,
          "total_lines": 61
        },
        {
          "sha": "79b6945",
          "author": "Luan Araújo",
          "date": "2025-04-24T12:32:03Z",
          "additions": 67,
          "deletions": 200,
          "total_lines": 267
        },
        {
          "sha": "3ee8cce",
          "author": "Luan Araújo",
          "date": "2025-04-14T17:52:51Z",
          "additions": 76,
          "deletions": 86,
          "total_lines": 162
        }
      ],
      "total_additions": 290,
      "total_deletions": 293,
      "total_lines": 583
    },
    "glpi": {
      "commits": [
        {
          "sha": "6f46693",
          "author": "Luan Araújo",
          "date": "2025-05-07T17:33:15Z",
          "additions": 1,
          "deletions": 1,
          "total_lines": 2
        },
        {
          "sha": "45d3d44",
          "author": "Thiago Mariano",
          "date": "2025-05-07T14:46:01Z",
          "additions": 4755554,
          "deletions": 0,
          "total_lines": 4755554
        }
      ],
      "total_additions": 4755555,
      "total_deletions": 1,
      "total_lines": 4755556
    },
    "sinforme": {
      "commits": [
        {
          "sha": "39f9d6a",
          "author": "Luan Araújo",
          "date": "2025-04-24T12:03:36Z",
          "additions": 69,
          "deletions": 84,
          "total_lines": 153
        },
        {
          "sha": "e5cfaf6",
          "author": "Luan Araújo",
          "date": "2025-04-11T20:17:25Z",
          "additions": 0,
          "deletions": 1,
          "total_lines": 1
        },
        {
          "sha": "379f8c3",
          "author": "Luan Araújo",
          "date": "2025-04-11T20:01:13Z",
          "additions": 1,
          "deletions": 1,
          "total_lines": 2
        },
        {
          "sha": "7a3f519",
          "author": "Luan Araújo",
          "date": "2025-04-11T20:00:47Z",
          "additions": 1615,
          "deletions": 10,
          "total_lines": 1625
        },
        {
          "sha": "337960c",
          "author": "Luan Araújo",
          "date": "2025-04-11T17:19:26Z",
          "additions": 238,
          "deletions": 37,
          "total_lines": 275
        }
      ],
      "total_additions": 1923,
      "total_deletions": 133,
      "total_lines": 2056
    },
    "atendimento_digital": {
      "commits": [
        {
          "sha": "cdde84b",
          "author": "Adelson",
          "date": "2025-04-02T14:09:23Z",
          "additions": 3,
          "deletions": 1,
          "total_lines": 4
        },
        {
          "sha": "a972649",
          "author": "Adelson",
          "date": "2025-02-18T16:50:11Z",
          "additions": 1,
          "deletions": 1,
          "total_lines": 2
        },
        {
          "sha": "4bd9520",
          "author": "Adelson",
          "date": "2025-02-12T14:12:38Z",
          "additions": 0,
          "deletions": 0,
          "total_lines": 0
        },
        {
          "sha": "d13186c",
          "author": "Danilo Torres",
          "date": "2025-01-20T17:42:54Z",
          "additions": 1,
          "deletions": 1,
          "total_lines": 2
        },
        {
          "sha": "87d4ece",
          "author": "Adelson",
          "date": "2025-01-15T19:18:55Z",
          "additions": 7,
          "deletions": 4,
          "total_lines": 11
        }
      ],
      "total_additions": 12,
      "total_deletions": 7,
      "total_lines": 19
    },
    "vem-diag": {
      "commits": [
        {
          "sha": "0d6f7bc",
          "author": "Luan Araújo",
          "date": "2025-04-01T13:02:10Z",
          "additions": 73,
          "deletions": 99,
          "total_lines": 172
        },
        {
          "sha": "61626d5",
          "author": "Luan Araújo",
          "date": "2025-04-01T12:58:13Z",
          "additions": 4,
          "deletions": 1,
          "total_lines": 5
        },
        {
          "sha": "03305c1",
          "author": "Luan Araújo",
          "date": "2025-04-01T12:55:48Z",
          "additions": 29318,
          "deletions": 0,
          "total_lines": 29318
        }
      ],
      "total_additions": 29395,
      "total_deletions": 100,
      "total_lines": 29495
    },
    "heskdesk": {
      "commits": [
        {
          "sha": "636ae8e",
          "author": "Danilo Torres",
          "date": "2025-03-10T14:54:59Z",
          "additions": 47,
          "deletions": 2,
          "total_lines": 49
        },
        {
          "sha": "1c6ce04",
          "author": "Danilo Torres",
          "date": "2025-02-26T14:48:32Z",
          "additions": 213569,
          "deletions": 0,
          "total_lines": 213569
        },
        {
          "sha": "4162e0b",
          "author": "Danilo Torres",
          "date": "2025-02-26T14:46:02Z",
          "additions": 1,
          "deletions": 0,
          "total_lines": 1
        }
      ],
      "total_additions": 213617,
      "total_deletions": 2,
      "total_lines": 213619
    }
  },
  "last_updated": "2025-06-29T22:38:22.002424-03:00"
}